lintquarto/__init__.py
lintquarto/__main__.py
lintquarto/args.py
lintquarto/converter.py
lintquarto/linelength.py
lintquarto/linters.py
lintquarto-0.7.0.dist-info/entry_points.txt
lintquarto-0.7.0.dist-info/licenses/LICENSE
lintquarto-0.7.0.dist-info/WHEEL
lintquarto-0.7.0.dist-info/METADATA
lintquarto-0.7.0.dist-info/RECORD
