Metadata-Version: 2.4
Name: lintquarto
Version: 0.7.0
Summary: Package for running linters, static type checkers and code analysis tools on python code in quarto (.qmd) files.
Keywords: lint,quarto,qmd,pylint,flake8,mypy
Author-email: Amy Heather <a.heather2@exeter.ac.uk>
Maintainer-email: Amy Heather <a.heather2@exeter.ac.uk>
Requires-Python: >=3.7
Classifier: Development Status :: 4 - Beta
Classifier: Intended Audience :: Science/Research
Classifier: Intended Audience :: End Users/Desktop
Classifier: Topic :: Software Development :: Quality Assurance
Classifier: Topic :: Text Processing :: Markup
Classifier: Topic :: Scientific/Engineering
Classifier: License :: OSI Approved :: MIT License
Classifier: Programming Language :: Python
Classifier: Programming Language :: Python :: 3.7
Classifier: Programming Language :: Python :: 3.8
Classifier: Programming Language :: Python :: 3.9
Classifier: Programming Language :: Python :: 3.10
Classifier: Programming Language :: Python :: 3.11
Classifier: Programming Language :: Python :: 3.12
Classifier: Programming Language :: Python :: 3.13
License-File: LICENSE
Requires-Dist: toml
Requires-Dist: pylint ; extra == "all"
Requires-Dist: flake8 ; extra == "all"
Requires-Dist: pyflakes ; extra == "all"
Requires-Dist: ruff ; extra == "all"
Requires-Dist: vulture ; extra == "all"
Requires-Dist: radon ; extra == "all"
Requires-Dist: pycodestyle ; extra == "all"
Requires-Dist: mypy ; extra == "all"
Requires-Dist: pydoclint ; extra == "all" and ( python_version >= '3.9')
Requires-Dist: pyright ; extra == "all"
Requires-Dist: pyrefly ; extra == "all"
Requires-Dist: pytype ; extra == "all" and ( python_version <= '3.12')
Requires-Dist: check-dependencies ; extra == "dev" and ( python_version >= '3.8')
Requires-Dist: flit ; extra == "dev"
Requires-Dist: genbadge ; extra == "dev"
Requires-Dist: grayskull ; extra == "dev"
Requires-Dist: jupyter ; extra == "dev"
Requires-Dist: pytest ; extra == "dev"
Requires-Dist: pytest-cov ; extra == "dev"
Requires-Dist: quartodoc ; extra == "dev"
Requires-Dist: twine ; extra == "dev"
Requires-Dist: types-toml ; extra == "dev" and ( python_version >= '3.8')
Project-URL: Bug Reports, https://github.com/lintquarto/lintquarto/issues
Project-URL: Home, https://github.com/lintquarto/lintquarto
Project-URL: Source, https://github.com/lintquarto/lintquarto
Provides-Extra: all
Provides-Extra: dev
